yandex_b2b_go/__init__.py
yandex_b2b_go/budget.py
yandex_b2b_go/client.py
yandex_b2b_go/department.py
yandex_b2b_go/eat.py
yandex_b2b_go/errors.py
yandex_b2b_go/geo.py
yandex_b2b_go/promocode.py
yandex_b2b_go/request.py
yandex_b2b_go/role.py
yandex_b2b_go/tanker.py
yandex_b2b_go/taxi.py
yandex_b2b_go/typing.py
yandex_b2b_go/user.py
yandex_b2b_go/utils.py
yandex_b2b_go/version.py
yandex_b2b_go-1.0.4.dist-info/LICENSE
yandex_b2b_go-1.0.4.dist-info/METADATA
yandex_b2b_go-1.0.4.dist-info/WHEEL
yandex_b2b_go-1.0.4.dist-info/top_level.txt
yandex_b2b_go-1.0.4.dist-info/RECORD
