Metadata-Version: 2.1
Name: yandex-b2b-go
Version: 1.0.4
Summary: Yandex GO for Business SDK
Author: Yandex LLC
Author-email: b2b-go@yandex-team.ru
License: MIT
Keywords: yandex,go,b2b,sdk,library,api
Classifier: Programming Language :: Python
Classifier: Programming Language :: Python :: 3
Classifier: Programming Language :: Python :: 3.8
Classifier: Programming Language :: Python :: 3.9
Classifier: Programming Language :: Python :: 3.10
Classifier: Programming Language :: Python :: 3.11
Classifier: Programming Language :: Python :: 3.12
Requires-Python: >=3.8
License-File: LICENSE
Requires-Dist: setuptools (>=65.5.1)
Requires-Dist: aiohttp (>=3.10.5)
Requires-Dist: pytest (>=8.1.1)
Requires-Dist: flake8 (==7.0.0)
Requires-Dist: Flake8-pyproject (==1.2.3)
Requires-Dist: mypy (==1.10)
Requires-Dist: pylint (==3.1.0)
Requires-Dist: black (==24.4.2)
Requires-Dist: isort (==5.13.2)
